stsci_rtd_theme/__init__.py
stsci_rtd_theme/layout.html
stsci_rtd_theme/theme.conf
stsci_rtd_theme/static/stsci.css
stsci_rtd_theme/static/stsci_pri_combo_mark_white.png
stsci_rtd_theme/static/fonts/Lato-Bold.ttf
stsci_rtd_theme/static/fonts/Lato-Regular.ttf
stsci_rtd_theme/static/fonts/RobotoSlab-Bold.ttf
stsci_rtd_theme/static/fonts/RobotoSlab-Regular.ttf
stsci_rtd_theme/static/fonts/fontawesome-webfont.woff
stsci_rtd_theme-1.0.1.dist-info/LICENSE
stsci_rtd_theme-1.0.1.dist-info/LICENSE.rst
stsci_rtd_theme-1.0.1.dist-info/METADATA
stsci_rtd_theme-1.0.1.dist-info/WHEEL
stsci_rtd_theme-1.0.1.dist-info/entry_points.txt
stsci_rtd_theme-1.0.1.dist-info/top_level.txt
stsci_rtd_theme-1.0.1.dist-info/RECORD
