Metadata-Version: 2.1
Name: stsci-rtd-theme
Version: 1.0.1
Summary: STScI Branded Sphinx theme
Author-email: STScI <help@stsci.edu>
License: BSD 3-Clause License
Project-URL: repository, https://github.com/spacetelescope/stsci_rtd_theme
Classifier: Development Status :: 5 - Production/Stable
Classifier: License :: OSI Approved :: BSD License
Classifier: Programming Language :: Python :: 2.7
Classifier: Programming Language :: Python :: 3
Classifier: Operating System :: OS Independent
Classifier: Topic :: Documentation
Classifier: Topic :: Software Development :: Documentation
Requires-Python: >=3.8
License-File: LICENSE
License-File: LICENSE.rst
Requires-Dist: sphinx >=1.3
Requires-Dist: sphinx-rtd-theme
